{
  "main": {
    "id": "dddc2987f5e83a42",
    "type": "split",
    "children": [
      {
        "id": "952e7fd53d134a75",
        "type": "tabs",
        "children": [
          {
            "id": "c572ab7c57a77853",
            "type": "leaf",
            "state": {
              "type": "markdown",
              "state": {
                "file": "Сайт/ТЗ/✅Активлог.md",
                "mode": "source",
                "source": false
              }
            }
          }
        ]
      }
    ],
    "direction": "vertical"
  },
  "left": {
    "id": "a75631c8c413f0c5",
    "type": "split",
    "children": [
      {
        "id": "fb03345e33842c52",
        "type": "tabs",
        "children": [
          {
            "id": "be66627d5ed9f28f",
            "type": "leaf",
            "state": {
              "type": "file-explorer",
              "state": {
                "sortOrder": "alphabetical"
              }
            }
          },
          {
            "id": "86408f95b55a914f",
            "type": "leaf",
            "state": {
              "type": "search",
              "state": {
                "query": "",
                "matchingCase": false,
                "explainSearch": false,
                "collapseAll": false,
                "extraContext": false,
                "sortOrder": "alphabetical"
              }
            }
          },
          {
            "id": "cfa8bb3ed06e8224",
            "type": "leaf",
            "state": {
              "type": "starred",
              "state": {}
            }
          },
          {
            "id": "317a10f2ae03763a",
            "type": "leaf",
            "state": {
              "type": "bookmarks",
              "state": {}
            }
          }
        ]
      }
    ],
    "direction": "horizontal",
    "width": 362.5
  },
  "right": {
    "id": "4179979e50cbc1ef",
    "type": "split",
    "children": [
      {
        "id": "e2a3ed9d99f75536",
        "type": "tabs",
        "children": [
          {
            "id": "1fdbbd7a7055b755",
            "type": "leaf",
            "state": {
              "type": "outgoing-link",
              "state": {
                "file": "Сайт/ТЗ/✅Активлог.md",
                "linksCollapsed": true,
                "unlinkedCollapsed": true
              }
            }
          },
          {
            "id": "7e02829cb1eb9c0a",
            "type": "leaf",
            "state": {
              "type": "tag",
              "state": {
                "sortOrder": "frequency",
                "useHierarchy": true
              }
            }
          },
          {
            "id": "f799f2a9fa9400ae",
            "type": "leaf",
            "state": {
              "type": "outline",
              "state": {
                "file": "Сайт/ТЗ/✅Активлог.md"
              }
            }
          },
          {
            "id": "0254568ac261d36b",
            "type": "leaf",
            "state": {
              "type": "backlink",
              "state": {
                "file": "Сайт/ТЗ/✅Активлог.md",
                "collapseAll": false,
                "extraContext": false,
                "sortOrder": "alphabetical",
                "showSearch": false,
                "searchQuery": "",
                "backlinkCollapsed": true,
                "unlinkedCollapsed": true
              }
            }
          },
          {
            "id": "071fa4db9c08e04e",
            "type": "leaf",
            "state": {
              "type": "advanced-tables-toolbar",
              "state": {}
            }
          },
          {
            "id": "c16cabecee8bcd0f",
            "type": "leaf",
            "state": {
              "type": "all-properties",
              "state": {
                "sortOrder": "frequency",
                "showSearch": false,
                "searchQuery": ""
              }
            }
          },
          {
            "id": "6435c6a31f7203ee",
            "type": "leaf",
            "state": {
              "type": "side-panel-control-view",
              "state": {}
            }
          }
        ],
        "currentTab": 2
      }
    ],
    "direction": "horizontal",
    "width": 200
  },
  "left-ribbon": {
    "hiddenItems": {
      "switcher:Open quick switcher": false,
      "graph:Open graph view": false,
      "canvas:Create new canvas": false,
      "daily-notes:Open today's daily note": false,
      "templates:Insert template": false,
      "command-palette:Open command palette": false,
      "random-note:Open random note": false,
      "vantage-obsidian:Vantage - Advanced search builder": false,
      "obsidian-markdown-formatting-assistant-plugin:Open Markdown Formatting Assistant": false,
      "obsidian-excalidraw-plugin:Create new drawing": false,
      "table-editor-obsidian:Advanced Tables Toolbar": false
    }
  },
  "active": "c572ab7c57a77853",
  "lastOpenFiles": [
    "Сайт/ТЗ/✅1-ая версия.md",
    "Сайт/ТЗ/✨2-ая версия.md",
    "Сайт/ТЗ.rar",
    "Сайт/ТЗ/Админка/Детализация функционала/✨2-ая версия/User history/Unauth Покупатель/Витрина UnAuth. Штучная. UH.md",
    "Сайт/ТЗ/Админка/Детализация функционала/✨2-ая версия/Данные для бекенда/Unauth Покупатель/Заказ неавторизованного покупателя. Бэк.md",
    "Сайт/ТЗ/Админка/Детализация функционала/✨2-ая версия/Данные для бекенда/Unauth Покупатель/Профиль товара. Разливной товар. Бэк.md",
    "Сайт/ТЗ/Админка/Детализация функционала/✨2-ая версия/User history/Unauth Покупатель/Заказ Unauth User. UH.md",
    "Сайт/ТЗ/Админка/Детализация функционала/✨2-ая версия/Данные для бекенда/Unauth Покупатель/Профиль товара. Штучный товар. Бэк.md",
    "Сайт/ТЗ/Админка/Детализация функционала/✨2-ая версия/Данные для бекенда/Unauth Покупатель/Витрина. Штучная. UnAuth. Бэк.md",
    "Сайт/ТЗ/Админка/Детализация функционала/✨2-ая версия/Данные для бекенда/Unauth Покупатель/Витрина. Разливная. Бэк.md",
    "Сайт/ТЗ/Админка/Детализация функционала/✨2-ая версия/User history/Unauth Покупатель/Витрина UnAuth. Разливная. UH.md",
    "Сайт/ТЗ/Админка/Детализация функционала/✨2-ая версия/Данные для бекенда/Структуры/Витрина.md",
    "Сайт/ТЗ/Админка/Детализация функционала/✨2-ая версия/Данные для бекенда/Структуры",
    "Сайт/ТЗ/Админка/Детализация функционала/✨2-ая версия/Данные для бекенда/Товаровед/Теги характеристик товаров. Бэк.md",
    "Сайт/ТЗ/Админка/Детализация функционала/✨2-ая версия/User history/Unauth Покупатель/Профиль товара. Разливной товар. UH.md",
    "Сайт/ТЗ/Админка/Детализация функционала/✨2-ая версия/User history/Unauth Покупатель/Профиль товара UnAuth. Штучный товар.  UH.md",
    "Сайт/ТЗ/Админка/Детализация функционала/✨2-ая версия/User history/Unauth Покупатель",
    "Сайт/ТЗ/Админка/Детализация функционала/✨2-ая версия/Данные для бекенда/Товаровед/Настройка рекомендаций витрин. Бэк.md",
    "Сайт/ТЗ/Админка/Детализация функционала/✨2-ая версия/User history/Товаровед/Настройка рекомендаций витрин. UH.md",
    "Сайт/ТЗ/Админка/Детализация функционала/✨2-ая версия/Данные для бекенда/Товаровед/Заполнение товара. Бэк.md",
    "Сайт/ТЗ/Админка/Детализация функционала/✨2-ая версия/Данные для бекенда/Товаровед/Заполнение витрин. Бэк.md",
    "Сайт/ТЗ/Админка/Детализация функционала/✨2-ая версия/User history/Товаровед/Заполнение товара. UH.md",
    "Сайт/ТЗ/Админка/Детализация функционала/✨2-ая версия/User history/Товаровед/Заполнение витрин. UH.md",
    "Сайт/ТЗ/Админка/Детализация функционала/✨2-ая версия/Уточнения/Теги характеристик товаров. Уточнение.md",
    "Сайт/ТЗ/Админка/Детализация функционала/✨2-ая версия/User history/Товаровед/Теги характеристик товаров. UH.md",
    "Сайт/ТЗ/Админка/Детализация функционала/✨2-ая версия/Уточнения/Создание и переименование витрин. Уточнение.md",
    "Сайт/ТЗ/Админка/Детализация функционала/✨2-ая версия/Данные для бекенда/Товаровед/Создание и переименование витрин. Бэк.md",
    "Сайт/ТЗ/Админка/Детализация функционала/✨2-ая версия/User history/Товаровед/Создание и редактирование каталогов. UH.md",
    "Сайт/ТЗ/Админка/Детализация функционала/✨2-ая версия/Данные для бекенда/Товаровед/Создание и редактирование каталогов. Бэк.md",
    "Сайт/ТЗ/Админка/Детализация функционала/✨2-ая версия/Данные для бекенда/Unauth Покупатель",
    "Сайт/ТЗ/Админка/Детализация функционала/✨2-ая версия/Уточнения",
    "Админка/Детализация функционала/✨2-ая версия",
    "Админка/Детализация функционала",
    "Сайт/ТЗ/Админка/Детализация функционала/✨2-ая версия/Данные для бекенда/Товаровед",
    "Сайт/ТЗ/Админка/Детализация функционала/✨2-ая версия/Данные для бекенда/Администратор",
    "Сайт/ТЗ/Админка/Детализация функционала/✨2-ая версия/Возможные ошибки",
    "Сайт/ТЗ/Админка/Связь со страницами покупателя/✨2-ая версия/_attachments/Иерархия каталогов-20240828194313847.webp",
    "Сайт/ТЗ/Общие моменты/_attachments/✨Иерархия товаров-20240828194444341.webp",
    "Сайт/ТЗ/Админка/Связь со страницами покупателя/✨2-ая версия/_attachments/Иерархия каталогов-20240824141917278.webp",
    "Сайт/ТЗ/Админка/Связь со страницами покупателя/✨2-ая версия/_attachments/Иерархия каталогов-20240828193700182.webp",
    "Сайт/ТЗ/Админка/Связь со страницами покупателя/✨2-ая версия/_attachments/Иерархия каталогов-20240822153409543.webp",
    "1C/УТ/_attachments/Ошибки-20240825121605592.webp",
    "Блог/Teletype/_attachments/Цвета-20240812193358146.webp",
    "Блог/Teletype/_attachments/Цвета-20240812193342033.webp",
    "Блог/Teletype/_attachments/Цвета-20240812193332834.webp",
    "Блог/Teletype/_attachments/Цвета-20240816145415665.webp",
    "Investment/Stocks and bonds/Untitled.canvas"
  ]
}